{
  "count": 608,
  "signers": [
    {
      "name": "Anna K.",
      "city": "Brno"
    },
    {
      "name": "Aneta J.",
      "city": "Brno"
    },
    {
      "name": "Adam S.",
      "city": "Brno"
    },
    {
      "name": "Marta E.",
      "city": "Brno"
    },
    {
      "name": "Vít P.",
      "city": "Brno"
    },
    {
      "name": "Marta E.",
      "city": "Brno"
    },
    {
      "name": "Cyril H.",
      "city": "Praha"
    },
    {
      "name": "Martin C.",
      "city": "Brno"
    },
    {
      "name": "Veronika P.",
      "city": "Brno"
    },
    {
      "name": "Jiří N.",
      "city": "Brno"
    },
    {
      "name": "Vanessa K.",
      "city": "Brno"
    },
    {
      "name": "Daniela U.",
      "city": "Brno"
    },
    {
      "name": "Štěpán K.",
      "city": ""
    },
    {
      "name": "Daniel K.",
      "city": "Hradec Králové"
    },
    {
      "name": "Dagmar K.",
      "city": "Brno"
    },
    {
      "name": "Jiří N.",
      "city": "Třebíč"
    },
    {
      "name": "Lenka Ř.",
      "city": "Brno"
    },
    {
      "name": "Radim N.",
      "city": "Prostějov"
    },
    {
      "name": "Linda V.",
      "city": "Brno"
    },
    {
      "name": "Věra G.",
      "city": "Brno"
    },
    {
      "name": "Petr K.",
      "city": "Střelice"
    },
    {
      "name": "Adam P.",
      "city": "Brno"
    },
    {
      "name": "Marie S.",
      "city": "Brno"
    },
    {
      "name": "Niki K.",
      "city": "Brno"
    },
    {
      "name": "Klára K.",
      "city": "Říčany"
    }
  ]
}